il_bank_validator/__init__.py
il_bank_validator/exceptions.py
il_bank_validator/validator.py
il_bank_validator-0.1.1.dist-info/licenses/LICENSE
il_bank_validator-0.1.1.dist-info/METADATA
il_bank_validator-0.1.1.dist-info/WHEEL
il_bank_validator-0.1.1.dist-info/top_level.txt
il_bank_validator-0.1.1.dist-info/RECORD
