Metadata-Version: 2.4
Name: il-bank-validator
Version: 0.1.1
Summary: Israeli Bank Account Validator based on MASAV rules (Dec 2024)
Author: Eliyahu Shteinman
License: MIT
Project-URL: Homepage, https://github.com/EliShteinman/il-bank-validator
Requires-Python: >=3.7
License-File: LICENSE
Dynamic: license-file
